setup.py
./loopjit/__init__.py
./loopjit/build_function.py
./loopjit/config.py
./loopjit/names.py
./loopjit/prims.py
./loopjit/run_function.py
./loopjit/syntax.py
loopjit.egg-info/PKG-INFO
loopjit.egg-info/SOURCES.txt
loopjit.egg-info/dependency_links.txt
loopjit.egg-info/top_level.txt
test/test_add.py
test/test_identity.py
test/test_subtypes.py
test/test_sum_loop.py